FinanceAgent/__init__.py
FinanceAgent/base.py
FinanceAgent/stock/__init__.py
FinanceAgent/stock/data_util_py3.py
FinanceAgent/stock/request_constants.py
FinanceAgent/stock/request_hk_stock_price_py3.py
FinanceAgent/stock/request_lse_stock_price.py
FinanceAgent/stock/request_stock_price_cn.py
FinanceAgent/stock/request_stock_price_india_nse.py
FinanceAgent/stock/request_us_stock_price_py3.py
financeagent-0.0.4.dist-info/METADATA
financeagent-0.0.4.dist-info/WHEEL
financeagent-0.0.4.dist-info/top_level.txt
financeagent-0.0.4.dist-info/RECORD
