Metadata-Version: 2.4
Name: FinanceAgent
Version: 0.0.4
Summary: Open API of realtime financial Market data, including Stock Price Quote from Global Market US Europe Asia, Major Index Dow/Nasdaq/S&P/Hang Seng/Nifty50, etc.
Author-email: aihubadmin@126.com
Project-URL: homepage, https://www.deepnlp.org
Project-URL: repository, https://github.com/AI-Hub-Admin/FinanceAgent
Keywords: API,Finance,AI Agent
Classifier: Development Status :: 3 - Alpha
Classifier: Intended Audience :: Developers
Classifier: Topic :: Software Development :: Build Tools
Classifier: License :: OSI Approved :: MIT License
Requires-Python: >=3.4
Dynamic: author-email
Dynamic: classifier
Dynamic: description
Dynamic: description-content-type
Dynamic: keywords
Dynamic: project-url
Dynamic: requires-python
Dynamic: summary
